<?xml version="1.0" encoding="utf-8" ?>
<c2layout>
    <name>Jogo</name>
    <sid>4650502934421703</sid>
    <event-sheet>Event sheet 1</event-sheet>
    <size>
        <width>414</width>
        <height>324</height>
    </size>
    <margins>
        <horizontal>500</horizontal>
        <vertical>500</vertical>
    </margins>
    <unbounded-scrolling>0</unbounded-scrolling>
    <layers>
        <layer name="Fundo" sid="6199299691916345">
            <initially-visible>1</initially-visible>
            <background-color>255,255,255</background-color>
            <transparent>0</transparent>
            <parallax>
                <x>1</x>
                <y>1</y>
            </parallax>
            <zoom-rate>1</zoom-rate>
            <opacity>1</opacity>
            <force-own-texture>0</force-own-texture>
            <global>0</global>
            <use-render-cells>0</use-render-cells>
            <blend-mode>0</blend-mode>
            <effect-fallback>0</effect-fallback>
            <instances>
                <instance type="TilemapFundo" uid="17">
                    <properties>
                        <initial-visibility>Visible</initial-visibility>
                        <tile-width>18</tile-width>
                        <tile-height>18</tile-height>
                        <tile-x-offset>0</tile-x-offset>
                        <tile-y-offset>0</tile-y-offset>
                        <tile-x-spacing>0</tile-x-spacing>
                        <tile-y-spacing>0</tile-y-spacing>
                        <seamless-mode>On</seamless-mode>
                    </properties>
                    <blend-mode>0</blend-mode>
                    <effect-fallback>0</effect-fallback>
                    <world>
                        <x>0</x>
                        <y>0</y>
                        <z>0</z>
                        <width>414</width>
                        <height>324</height>
                        <depth>0</depth>
                        <hotspotX>0</hotspotX>
                        <hotspotY>0</hotspotY>
                        <opacity>1</opacity>
                    </world>
                    <tilemap-data>
                        <width>23</width>
                        <height>18</height>
                        <max-width>23</max-width>
                        <max-height>23</max-height>
                        <data>83,83,83,83,83,83,83,83,83,83,83,83,83,83,83,83,83,43,83,83,20,40,60,83,20,60,84,84,84,84,84,83,20,60,84,84,84,83,20,60,43,84,84,21,41,61,83,21,61,84,84,84,84,84,83,21,61,84,84,84,83,21,61,43,84,84,21,41,61,83,21,61,84,84,84,84,84,83,21,61,84,84,84,83,21,61,43,84,84,21,41,61,83,21,41,84,84,84,84,84,83,21,61,30,84,84,83,21,61,43,84,84,21,41,61,83,21,61,84,84,84,84,84,83,21,61,84,84,84,83,21,61,43,84,84,21,41,61,83,21,61,84,84,84,84,84,83,21,61,84,84,84,83,21,61,43,84,84,21,41,61,83,21,61,84,84,84,84,84,83,21,61,84,84,84,83,21,61,43,84,84,21,41,61,83,21,61,84,84,84,84,84,83,22,62,84,84,84,83,21,61,43,84,84,21,41,61,83,21,61,84,84,84,84,84,84,84,84,84,84,84,83,21,61,43,84,84,21,41,61,83,21,61,84,84,84,84,84,84,84,84,84,84,84,83,21,61,43,84,84,21,41,61,83,21,61,84,84,84,84,84,83,20,60,84,84,84,83,21,61,63,84,84,21,41,61,83,21,61,84,84,84,84,84,83,21,61,84,84,84,83,21,61,43,84,84,21,41,61,83,83,83,83,83,83,83,83,83,22,62,84,84,84,83,21,61,43,83,83,21,41,61,83,21,61,84,84,84,84,84,84,84,84,84,84,84,83,21,61,43,84,84,21,41,61,83,21,61,84,84,84,84,84,84,84,84,84,84,84,83,21,61,43,84,84,21,41,61,83,21,61,84,84,84,83,83,83,83,83,83,84,84,83,21,61,43,84,84,21,41,61,83,21,41,84,84,84,83,21,61,84,84,84,84,84,83,21,61,43,84,84,21,41,61,83,21,61,84,84,84,83,21,61,84,84,84,84,84,83,21,61,43,84,84,21,41,61,83,21,61,84,84,84,83,21,61,84,84,84,84,84,83,21,61,43,84,84,21,41,61,83,21,61,84,84,84,83,21,61,84,84,84,84,84,83,21,61,43,84,84,21,41,61,83,22,61,84,84,84,83,22,62,84,84,84,84,84,83,22,62,43,84,84,21,41,61,83,83,83,83,83,83,83,83,83,83,83,83,83,83,83,83,83,43,83,83,22,42,62</data>
                    </tilemap-data>
                </instance>
            </instances>
            <effects />
        </layer>
        <layer name="Jogo" sid="911430438677374">
            <initially-visible>1</initially-visible>
            <background-color>255,255,255</background-color>
            <transparent>1</transparent>
            <parallax>
                <x>1</x>
                <y>1</y>
            </parallax>
            <zoom-rate>1</zoom-rate>
            <opacity>1</opacity>
            <force-own-texture>0</force-own-texture>
            <global>0</global>
            <use-render-cells>0</use-render-cells>
            <blend-mode>0</blend-mode>
            <effect-fallback>0</effect-fallback>
            <instances>
                <instance type="Tilemap" uid="18">
                    <properties>
                        <initial-visibility>Visible</initial-visibility>
                        <tile-width>18</tile-width>
                        <tile-height>18</tile-height>
                        <tile-x-offset>0</tile-x-offset>
                        <tile-y-offset>0</tile-y-offset>
                        <tile-x-spacing>0</tile-x-spacing>
                        <tile-y-spacing>0</tile-y-spacing>
                        <seamless-mode>On</seamless-mode>
                    </properties>
                    <blend-mode>0</blend-mode>
                    <effect-fallback>0</effect-fallback>
                    <world>
                        <x>0</x>
                        <y>0</y>
                        <z>0</z>
                        <width>414</width>
                        <height>324</height>
                        <depth>0</depth>
                        <hotspotX>0</hotspotX>
                        <hotspotY>0</hotspotY>
                        <opacity>1</opacity>
                    </world>
                    <tilemap-data>
                        <width>23</width>
                        <height>18</height>
                        <max-width>23</max-width>
                        <max-height>23</max-height>
                        <data>-1,-1,-1,-1,-1,-1,-1,-1,-1,-1,-1,-1,-1,-1,-1,-1,-1,-1,-1,-1,-1,-1,-1,-1,-1,-1,-1,-1,-1,-1,-1,-1,-1,-1,-1,-1,-1,-1,-1,-1,-1,-1,-1,-1,-1,-1,-1,36,56,76,-1,-1,-1,-1,-1,4,-1,-1,-1,-1,-1,-1,-1,-1,-1,-1,-1,-1,-1,-1,4,-1,-1,-1,29,-1,-1,-1,-1,-1,29,-1,-1,-1,109,-1,-1,-1,-1,-1,-1,-1,-1,-1,57,77,-1,30,-1,-1,-1,109,52,72,-1,-1,-1,110,-1,-1,-1,-1,-1,-1,-1,-1,109,-1,-1,-1,31,-1,-1,-1,111,-1,31,-1,-1,-1,111,-1,-1,-1,-1,-1,-1,-1,-1,110,58,78,-1,-1,-1,-1,-1,-1,-1,-1,-1,-1,-1,-1,-1,-1,-1,-1,-1,-1,-1,-1,111,-1,-1,-1,-1,-1,-1,-1,4,-1,-1,-1,-1,-1,-1,-1,-1,-1,-1,-1,-1,-1,-1,-1,58,78,-1,29,-1,-1,-1,-1,-1,-1,-1,-1,-1,4,-1,-1,-1,-1,-1,-1,-1,-1,4,-1,-1,-1,30,-1,-1,-1,-1,-1,-1,-1,-1,-1,-1,-1,-1,-1,-1,-1,-1,-1,-1,-1,-1,-1,-1,31,-1,-1,-1,-1,-1,-1,-1,-1,-1,-1,-1,-1,-1,-1,-1,-1,-1,-1,70,-1,-1,-1,-1,-1,-1,-1,-1,-1,-1,-1,-1,-1,87,107,-1,-1,-1,-1,-1,-1,-1,-1,-1,-1,-1,-1,-1,-1,-1,102,-1,-1,-1,-1,-1,-1,-1,-1,-1,-1,-1,-1,-1,-1,-1,-1,-1,-1,-1,-1,-1,-1,-1,-1,-1,-1,-1,-1,-1,-1,-1,-1,-1,-1,-1,-1,-1,-1,-1,-1,-1,-1,-1,-1,-1,-1,-1,-1,-1,-1,-1,4,-1,-1,-1,-1,-1,-1,-1,-1,24,-1,-1,-1,-1,-1,-1,-1,-1,-1,-1,-1,-1,-1,-1,-1,-1,-1,-1,-1,-1,-1,-1,-1,-1,-1,-1,-1,-1,-1,-1,-1,-1,-1,-1,-1,-1,-1,-1,-1,-1,-1,-1,-1,-1,-1,-1,57,77,-1,-1,-1,-1,-1,100,-1,101,-1,-1,-1,109,-1,-1,-1,-1,-1,-1,-1,-1,-1,-1,-1,-1,-1,-1,5,-1,-1,-1,-1,-1,-1,-1,110,-1,-1,-1,-1,-1,-1,-1,-1,4,-1,-1,-1,-1,-1,-1,-1,59,79,-1,-1,-1,-1,111,-1,-1,-1,-1,-1,-1,-1,-1,-1,96,116,-1,-1,-1,25,-1,-1,-1,-1,-1,-1,-1,-1,-1,-1,-1,-1,-1,-1,-1,-1,-1,-1,-1,-1,-1,-1,-1,-1,101,-1,-1,-1,100,-1,-1,-1,-1,-1,-1,-1,-1,-1,-1,-1,-1,-1,-1,-1,-1,-1,-1,-1,-1,-1,-1,-1,-1,-1,-1,-1,-1,-1,-1,-1,-1</data>
                    </tilemap-data>
                </instance>
                <instance type="Banheiro" uid="12">
                    <properties>
                        <initial-visibility>Invisible</initial-visibility>
                        <initial-animation>Default</initial-animation>
                        <initial-frame>0</initial-frame>
                        <collisions>Enabled</collisions>
                    </properties>
                    <blend-mode>0</blend-mode>
                    <effect-fallback>0</effect-fallback>
                    <world>
                        <x>375.828216553</x>
                        <y>74.556350708</y>
                        <z>0</z>
                        <width>13.666625977</width>
                        <height>35.421123505</height>
                        <depth>0</depth>
                        <hotspotX>1</hotspotX>
                        <hotspotY>1</hotspotY>
                        <angle>0</angle>
                        <opacity>1</opacity>
                    </world>
                </instance>
                <instance type="Computador" uid="9">
                    <properties>
                        <initial-visibility>Invisible</initial-visibility>
                        <initial-animation>Default</initial-animation>
                        <initial-frame>0</initial-frame>
                        <collisions>Enabled</collisions>
                    </properties>
                    <blend-mode>0</blend-mode>
                    <effect-fallback>0</effect-fallback>
                    <world>
                        <x>91.254104614</x>
                        <y>216.709915161</y>
                        <z>0</z>
                        <width>19.250740051</width>
                        <height>27.335586548</height>
                        <depth>0</depth>
                        <hotspotX>1</hotspotX>
                        <hotspotY>1</hotspotY>
                        <angle>0</angle>
                        <opacity>1</opacity>
                    </world>
                </instance>
                <instance type="Geladeira" uid="13">
                    <properties>
                        <initial-visibility>Invisible</initial-visibility>
                        <initial-animation>Default</initial-animation>
                        <initial-frame>0</initial-frame>
                        <collisions>Enabled</collisions>
                    </properties>
                    <blend-mode>0</blend-mode>
                    <effect-fallback>0</effect-fallback>
                    <world>
                        <x>53.921829224</x>
                        <y>62.299068451</y>
                        <z>0</z>
                        <width>15.395446777</width>
                        <height>31.798233032</height>
                        <depth>0</depth>
                        <hotspotX>1</hotspotX>
                        <hotspotY>1</hotspotY>
                        <angle>0</angle>
                        <opacity>1</opacity>
                    </world>
                </instance>
                <instance type="Cama" uid="15">
                    <properties>
                        <initial-visibility>Invisible</initial-visibility>
                        <initial-animation>Default</initial-animation>
                        <initial-frame>0</initial-frame>
                        <collisions>Enabled</collisions>
                    </properties>
                    <blend-mode>0</blend-mode>
                    <effect-fallback>0</effect-fallback>
                    <world>
                        <x>359.396240234</x>
                        <y>195.231994629</y>
                        <z>0</z>
                        <width>14.918334961</width>
                        <height>31.60395813</height>
                        <depth>0</depth>
                        <hotspotX>1</hotspotX>
                        <hotspotY>1</hotspotY>
                        <angle>0</angle>
                        <opacity>1</opacity>
                    </world>
                </instance>
                <instance type="Parede" uid="21">
                    <properties>
                        <initial-visibility>Invisible</initial-visibility>
                        <initial-animation>Default</initial-animation>
                        <initial-frame>0</initial-frame>
                        <collisions>Enabled</collisions>
                    </properties>
                    <behavior-instances>
                        <behavior-instance type="Solid">
                            <properties>
                                <initial-state>Enabled</initial-state>
                            </properties>
                        </behavior-instance>
                    </behavior-instances>
                    <blend-mode>0</blend-mode>
                    <effect-fallback>0</effect-fallback>
                    <world>
                        <x>413.69619751</x>
                        <y>271.430480957</y>
                        <z>0</z>
                        <width>17.122741699</width>
                        <height>270.529785156</height>
                        <depth>0</depth>
                        <hotspotX>1</hotspotX>
                        <hotspotY>1</hotspotY>
                        <angle>0</angle>
                        <opacity>1</opacity>
                    </world>
                </instance>
                <instance type="Parede" uid="22">
                    <properties>
                        <initial-visibility>Invisible</initial-visibility>
                        <initial-animation>Default</initial-animation>
                        <initial-frame>0</initial-frame>
                        <collisions>Enabled</collisions>
                    </properties>
                    <behavior-instances>
                        <behavior-instance type="Solid">
                            <properties>
                                <initial-state>Enabled</initial-state>
                            </properties>
                        </behavior-instance>
                    </behavior-instances>
                    <blend-mode>0</blend-mode>
                    <effect-fallback>0</effect-fallback>
                    <world>
                        <x>17.638092041</x>
                        <y>270.37878418</y>
                        <z>0</z>
                        <width>17.122741699</width>
                        <height>270.529785156</height>
                        <depth>0</depth>
                        <hotspotX>1</hotspotX>
                        <hotspotY>1</hotspotY>
                        <angle>0</angle>
                        <opacity>1</opacity>
                    </world>
                </instance>
                <instance type="Parede" uid="23">
                    <properties>
                        <initial-visibility>Invisible</initial-visibility>
                        <initial-animation>Default</initial-animation>
                        <initial-frame>0</initial-frame>
                        <collisions>Enabled</collisions>
                    </properties>
                    <behavior-instances>
                        <behavior-instance type="Solid">
                            <properties>
                                <initial-state>Enabled</initial-state>
                            </properties>
                        </behavior-instance>
                    </behavior-instances>
                    <blend-mode>0</blend-mode>
                    <effect-fallback>0</effect-fallback>
                    <world>
                        <x>305.74395752</x>
                        <y>216.403060913</y>
                        <z>0</z>
                        <width>17.122741699</width>
                        <height>107.199615479</height>
                        <depth>0</depth>
                        <hotspotX>1</hotspotX>
                        <hotspotY>1</hotspotY>
                        <angle>0</angle>
                        <opacity>1</opacity>
                    </world>
                </instance>
                <instance type="Parede" uid="25">
                    <properties>
                        <initial-visibility>Invisible</initial-visibility>
                        <initial-animation>Default</initial-animation>
                        <initial-frame>0</initial-frame>
                        <collisions>Enabled</collisions>
                    </properties>
                    <behavior-instances>
                        <behavior-instance type="Solid">
                            <properties>
                                <initial-state>Enabled</initial-state>
                            </properties>
                        </behavior-instance>
                    </behavior-instances>
                    <blend-mode>0</blend-mode>
                    <effect-fallback>0</effect-fallback>
                    <world>
                        <x>251.767700195</x>
                        <y>182.404983521</y>
                        <z>0</z>
                        <width>17.122741699</width>
                        <height>181.854690552</height>
                        <depth>0</depth>
                        <hotspotX>1</hotspotX>
                        <hotspotY>1</hotspotY>
                        <angle>0</angle>
                        <opacity>1</opacity>
                    </world>
                </instance>
                <instance type="Parede" uid="27">
                    <properties>
                        <initial-visibility>Invisible</initial-visibility>
                        <initial-animation>Default</initial-animation>
                        <initial-frame>0</initial-frame>
                        <collisions>Enabled</collisions>
                    </properties>
                    <behavior-instances>
                        <behavior-instance type="Solid">
                            <properties>
                                <initial-state>Enabled</initial-state>
                            </properties>
                        </behavior-instance>
                    </behavior-instances>
                    <blend-mode>0</blend-mode>
                    <effect-fallback>0</effect-fallback>
                    <world>
                        <x>395.470123291</x>
                        <y>147.355621338</y>
                        <z>0</z>
                        <width>107.199554443</width>
                        <height>38.152023315</height>
                        <depth>0</depth>
                        <hotspotX>1</hotspotX>
                        <hotspotY>1</hotspotY>
                        <angle>0</angle>
                        <opacity>1</opacity>
                    </world>
                </instance>
                <instance type="Parede" uid="28">
                    <properties>
                        <initial-visibility>Invisible</initial-visibility>
                        <initial-animation>Default</initial-animation>
                        <initial-frame>0</initial-frame>
                        <collisions>Enabled</collisions>
                    </properties>
                    <behavior-instances>
                        <behavior-instance type="Solid">
                            <properties>
                                <initial-state>Enabled</initial-state>
                            </properties>
                        </behavior-instance>
                    </behavior-instances>
                    <blend-mode>0</blend-mode>
                    <effect-fallback>0</effect-fallback>
                    <world>
                        <x>251.417022705</x>
                        <y>182.404724121</y>
                        <z>0</z>
                        <width>52.172088623</width>
                        <height>38.152023315</height>
                        <depth>0</depth>
                        <hotspotX>1</hotspotX>
                        <hotspotY>1</hotspotY>
                        <angle>0</angle>
                        <opacity>1</opacity>
                    </world>
                </instance>
                <instance type="Parede" uid="29">
                    <properties>
                        <initial-visibility>Invisible</initial-visibility>
                        <initial-animation>Default</initial-animation>
                        <initial-frame>0</initial-frame>
                        <collisions>Enabled</collisions>
                    </properties>
                    <behavior-instances>
                        <behavior-instance type="Solid">
                            <properties>
                                <initial-state>Enabled</initial-state>
                            </properties>
                        </behavior-instance>
                    </behavior-instances>
                    <blend-mode>0</blend-mode>
                    <effect-fallback>0</effect-fallback>
                    <world>
                        <x>160.989624023</x>
                        <y>182.755493164</y>
                        <z>0</z>
                        <width>160.824707031</width>
                        <height>38.152023315</height>
                        <depth>0</depth>
                        <hotspotX>1</hotspotX>
                        <hotspotY>1</hotspotY>
                        <angle>0</angle>
                        <opacity>1</opacity>
                    </world>
                </instance>
                <instance type="Parede" uid="31">
                    <properties>
                        <initial-visibility>Invisible</initial-visibility>
                        <initial-animation>Default</initial-animation>
                        <initial-frame>0</initial-frame>
                        <collisions>Enabled</collisions>
                    </properties>
                    <behavior-instances>
                        <behavior-instance type="Solid">
                            <properties>
                                <initial-state>Enabled</initial-state>
                            </properties>
                        </behavior-instance>
                    </behavior-instances>
                    <blend-mode>0</blend-mode>
                    <effect-fallback>0</effect-fallback>
                    <world>
                        <x>243.00491333</x>
                        <y>38.702575684</y>
                        <z>0</z>
                        <width>242.49005127</width>
                        <height>38.152023315</height>
                        <depth>0</depth>
                        <hotspotX>1</hotspotX>
                        <hotspotY>1</hotspotY>
                        <angle>0</angle>
                        <opacity>1</opacity>
                    </world>
                </instance>
                <instance type="Parede" uid="33">
                    <properties>
                        <initial-visibility>Invisible</initial-visibility>
                        <initial-animation>Default</initial-animation>
                        <initial-frame>0</initial-frame>
                        <collisions>Enabled</collisions>
                    </properties>
                    <behavior-instances>
                        <behavior-instance type="Solid">
                            <properties>
                                <initial-state>Enabled</initial-state>
                            </properties>
                        </behavior-instance>
                    </behavior-instances>
                    <blend-mode>0</blend-mode>
                    <effect-fallback>0</effect-fallback>
                    <world>
                        <x>413.345062256</x>
                        <y>37.300636292</y>
                        <z>0</z>
                        <width>242.49005127</width>
                        <height>38.152023315</height>
                        <depth>0</depth>
                        <hotspotX>1</hotspotX>
                        <hotspotY>1</hotspotY>
                        <angle>0</angle>
                        <opacity>1</opacity>
                    </world>
                </instance>
                <instance type="Parede" uid="34">
                    <properties>
                        <initial-visibility>Invisible</initial-visibility>
                        <initial-animation>Default</initial-animation>
                        <initial-frame>0</initial-frame>
                        <collisions>Enabled</collisions>
                    </properties>
                    <behavior-instances>
                        <behavior-instance type="Solid">
                            <properties>
                                <initial-state>Enabled</initial-state>
                            </properties>
                        </behavior-instance>
                    </behavior-instances>
                    <blend-mode>0</blend-mode>
                    <effect-fallback>0</effect-fallback>
                    <world>
                        <x>412.994628906</x>
                        <y>291.05770874</y>
                        <z>0</z>
                        <width>411.778747559</width>
                        <height>38.152023315</height>
                        <depth>0</depth>
                        <hotspotX>1</hotspotX>
                        <hotspotY>1</hotspotY>
                        <angle>0</angle>
                        <opacity>1</opacity>
                    </world>
                </instance>
                <instance type="PC" uid="35">
                    <properties>
                        <initial-visibility>Invisible</initial-visibility>
                        <initial-animation>Default</initial-animation>
                        <initial-frame>0</initial-frame>
                        <collisions>Enabled</collisions>
                    </properties>
                    <blend-mode>0</blend-mode>
                    <effect-fallback>0</effect-fallback>
                    <world>
                        <x>81.31452179</x>
                        <y>199.579223633</y>
                        <z>0</z>
                        <width>18</width>
                        <height>20</height>
                        <depth>0</depth>
                        <hotspotX>0.5</hotspotX>
                        <hotspotY>0.5</hotspotY>
                        <angle>0</angle>
                        <opacity>1</opacity>
                    </world>
                </instance>
                <instance type="Player" uid="0">
                    <properties>
                        <initial-visibility>Visible</initial-visibility>
                        <initial-animation>Default</initial-animation>
                        <initial-frame>0</initial-frame>
                        <collisions>Enabled</collisions>
                    </properties>
                    <behavior-instances>
                        <behavior-instance type="8Direction">
                            <properties>
                                <max-speed>80</max-speed>
                                <acceleration>300</acceleration>
                                <deceleration>600</deceleration>
                                <directions>4 directions</directions>
                                <set-angle>No</set-angle>
                                <default-controls>Yes</default-controls>
                                <initial-state>Enabled</initial-state>
                            </properties>
                        </behavior-instance>
                        <behavior-instance type="ScrollTo">
                            <properties>
                                <initial-state>Enabled</initial-state>
                            </properties>
                        </behavior-instance>
                    </behavior-instances>
                    <blend-mode>0</blend-mode>
                    <effect-fallback>0</effect-fallback>
                    <world>
                        <x>184.744689941</x>
                        <y>221.55645752</y>
                        <z>0</z>
                        <width>18</width>
                        <height>36</height>
                        <depth>0</depth>
                        <hotspotX>0.5</hotspotX>
                        <hotspotY>0.5</hotspotY>
                        <angle>0</angle>
                        <opacity>1</opacity>
                    </world>
                </instance>
                <instance type="Pjogo" uid="36">
                    <properties>
                        <rate>1</rate>
                        <spray-cone>360</spray-cone>
                        <type>One-shot</type>
                        <initial-particle-properties></initial-particle-properties>
                        <speed>50</speed>
                        <size>18</size>
                        <opacity>100</opacity>
                        <grow-rate>0</grow-rate>
                        <x-randomiser>0</x-randomiser>
                        <y-randomiser>0</y-randomiser>
                        <speed-randomiser->0</speed-randomiser->
                        <size-randomiser>0</size-randomiser>
                        <grow-rate-randomiser>0</grow-rate-randomiser>
                        <particle-lifetime-properties></particle-lifetime-properties>
                        <acceleration>0</acceleration>
                        <gravity>0</gravity>
                        <angle-randomiser>0</angle-randomiser>
                        <speed-randomiser>800</speed-randomiser>
                        <opacity-randomiser>0</opacity-randomiser>
                        <destroy-mode>Fade to invisible</destroy-mode>
                        <timeout>1</timeout>
                    </properties>
                    <blend-mode>0</blend-mode>
                    <effect-fallback>0</effect-fallback>
                    <world>
                        <x>-70</x>
                        <y>114</y>
                        <z>0</z>
                        <width>128</width>
                        <height>128</height>
                        <depth>0</depth>
                        <hotspotX>0</hotspotX>
                        <hotspotY>0.5</hotspotY>
                        <angle>-1.57079649</angle>
                        <opacity>1</opacity>
                    </world>
                </instance>
                <instance type="Pfome" uid="24">
                    <properties>
                        <rate>1</rate>
                        <spray-cone>360</spray-cone>
                        <type>One-shot</type>
                        <initial-particle-properties></initial-particle-properties>
                        <speed>50</speed>
                        <size>18</size>
                        <opacity>100</opacity>
                        <grow-rate>0</grow-rate>
                        <x-randomiser>0</x-randomiser>
                        <y-randomiser>0</y-randomiser>
                        <speed-randomiser->0</speed-randomiser->
                        <size-randomiser>0</size-randomiser>
                        <grow-rate-randomiser>0</grow-rate-randomiser>
                        <particle-lifetime-properties></particle-lifetime-properties>
                        <acceleration>0</acceleration>
                        <gravity>0</gravity>
                        <angle-randomiser>0</angle-randomiser>
                        <speed-randomiser>800</speed-randomiser>
                        <opacity-randomiser>0</opacity-randomiser>
                        <destroy-mode>Fade to invisible</destroy-mode>
                        <timeout>1</timeout>
                    </properties>
                    <blend-mode>0</blend-mode>
                    <effect-fallback>0</effect-fallback>
                    <world>
                        <x>528.749633789</x>
                        <y>29.892150879</y>
                        <z>0</z>
                        <width>128</width>
                        <height>128</height>
                        <depth>0</depth>
                        <hotspotX>0</hotspotX>
                        <hotspotY>0.5</hotspotY>
                        <angle>0</angle>
                        <opacity>1</opacity>
                    </world>
                </instance>
                <instance type="Psono" uid="26">
                    <properties>
                        <rate>1</rate>
                        <spray-cone>360</spray-cone>
                        <type>One-shot</type>
                        <initial-particle-properties></initial-particle-properties>
                        <speed>50</speed>
                        <size>18</size>
                        <opacity>100</opacity>
                        <grow-rate>0</grow-rate>
                        <x-randomiser>0</x-randomiser>
                        <y-randomiser>0</y-randomiser>
                        <speed-randomiser->0</speed-randomiser->
                        <size-randomiser>0</size-randomiser>
                        <grow-rate-randomiser>0</grow-rate-randomiser>
                        <particle-lifetime-properties></particle-lifetime-properties>
                        <acceleration>0</acceleration>
                        <gravity>0</gravity>
                        <angle-randomiser>0</angle-randomiser>
                        <speed-randomiser>800</speed-randomiser>
                        <opacity-randomiser>0</opacity-randomiser>
                        <destroy-mode>Fade to invisible</destroy-mode>
                        <timeout>1</timeout>
                    </properties>
                    <blend-mode>0</blend-mode>
                    <effect-fallback>0</effect-fallback>
                    <world>
                        <x>531.459777832</x>
                        <y>167.398849487</y>
                        <z>0</z>
                        <width>128</width>
                        <height>128</height>
                        <depth>0</depth>
                        <hotspotX>0</hotspotX>
                        <hotspotY>0.5</hotspotY>
                        <angle>0</angle>
                        <opacity>1</opacity>
                    </world>
                </instance>
                <instance type="Pxixi" uid="30">
                    <properties>
                        <rate>1</rate>
                        <spray-cone>360</spray-cone>
                        <type>One-shot</type>
                        <initial-particle-properties></initial-particle-properties>
                        <speed>50</speed>
                        <size>18</size>
                        <opacity>100</opacity>
                        <grow-rate>0</grow-rate>
                        <x-randomiser>0</x-randomiser>
                        <y-randomiser>0</y-randomiser>
                        <speed-randomiser->0</speed-randomiser->
                        <size-randomiser>0</size-randomiser>
                        <grow-rate-randomiser>0</grow-rate-randomiser>
                        <particle-lifetime-properties></particle-lifetime-properties>
                        <acceleration>0</acceleration>
                        <gravity>0</gravity>
                        <angle-randomiser>0</angle-randomiser>
                        <speed-randomiser>800</speed-randomiser>
                        <opacity-randomiser>0</opacity-randomiser>
                        <destroy-mode>Fade to invisible</destroy-mode>
                        <timeout>1</timeout>
                    </properties>
                    <blend-mode>0</blend-mode>
                    <effect-fallback>0</effect-fallback>
                    <world>
                        <x>-191.970275879</x>
                        <y>278.4871521</y>
                        <z>0</z>
                        <width>128</width>
                        <height>128</height>
                        <depth>0</depth>
                        <hotspotX>0</hotspotX>
                        <hotspotY>0.5</hotspotY>
                        <angle>0</angle>
                        <opacity>1</opacity>
                    </world>
                </instance>
            </instances>
            <effects />
        </layer>
        <layer name="HUD" sid="599940028694683">
            <initially-visible>1</initially-visible>
            <background-color>255,255,255</background-color>
            <transparent>1</transparent>
            <parallax>
                <x>0</x>
                <y>0</y>
            </parallax>
            <zoom-rate>1</zoom-rate>
            <opacity>1</opacity>
            <force-own-texture>0</force-own-texture>
            <global>0</global>
            <use-render-cells>0</use-render-cells>
            <blend-mode>0</blend-mode>
            <effect-fallback>0</effect-fallback>
            <instances>
                <instance type="FundoTela" uid="8">
                    <properties>
                        <initial-visibility>Visible</initial-visibility>
                        <initial-animation>Default</initial-animation>
                        <initial-frame>0</initial-frame>
                        <collisions>Enabled</collisions>
                    </properties>
                    <blend-mode>0</blend-mode>
                    <effect-fallback>0</effect-fallback>
                    <world>
                        <x>320</x>
                        <y>180</y>
                        <z>0</z>
                        <width>320</width>
                        <height>36</height>
                        <depth>0</depth>
                        <hotspotX>1</hotspotX>
                        <hotspotY>1</hotspotY>
                        <angle>0</angle>
                        <opacity>1</opacity>
                    </world>
                </instance>
                <instance type="TilemapHUD" uid="19">
                    <properties>
                        <initial-visibility>Visible</initial-visibility>
                        <tile-width>18</tile-width>
                        <tile-height>18</tile-height>
                        <tile-x-offset>0</tile-x-offset>
                        <tile-y-offset>0</tile-y-offset>
                        <tile-x-spacing>0</tile-x-spacing>
                        <tile-y-spacing>0</tile-y-spacing>
                        <seamless-mode>On</seamless-mode>
                    </properties>
                    <blend-mode>0</blend-mode>
                    <effect-fallback>0</effect-fallback>
                    <world>
                        <x>0</x>
                        <y>144</y>
                        <z>0</z>
                        <width>320</width>
                        <height>36</height>
                        <depth>0</depth>
                        <hotspotX>0</hotspotX>
                        <hotspotY>0</hotspotY>
                        <opacity>1</opacity>
                    </world>
                    <tilemap-data>
                        <width>17</width>
                        <height>2</height>
                        <max-width>17</max-width>
                        <max-height>10</max-height>
                        <data>-1,-1,-1,-1,-1,-1,-1,-1,-1,-1,103,129,-1,-1,-1,-1,-1,-1,-1,-1,123,123,-1,-1,-1,-1,-1,-1,-1,-1,124,124,-1,-1,-1,-1,-1,-1,-1,-1,125,124,-1,-1,-1,-1,-1,-1,-1,-1,-1,124,-1,-1,-1,-1,-1,-1,-1,-1,-1,124,-1,-1,-1,-1,-1,-1,-1,-1,104,124,-1,-1,-1,-1,-1,-1,-1,-1,123,124,-1,-1,-1,-1,-1,-1,-1,-1,124,125,-1,-1,-1,-1,-1,-1,-1,-1,125,-1,-1,-1,-1,-1,-1,-1,-1,-1,-1,149,-1,-1,-1,-1,-1,-1,-1,-1,-1,123,-1,-1,-1,-1,-1,-1,-1,-1,105,124,-1,-1,-1,-1,-1,-1,-1,-1,123,124,-1,-1,-1,-1,-1,-1,-1,-1,124,124,-1,-1,-1,-1,-1,-1,-1,-1,125,125,-1,-1,-1,-1,-1,-1,-1,-1</data>
                    </tilemap-data>
                </instance>
                <instance type="Jogo" uid="10">
                    <properties>
                        <initial-visibility>Visible</initial-visibility>
                        <initial-animation>Default</initial-animation>
                        <initial-frame>0</initial-frame>
                        <collisions>Enabled</collisions>
                    </properties>
                    <blend-mode>0</blend-mode>
                    <effect-fallback>0</effect-fallback>
                    <world>
                        <x>38</x>
                        <y>175</y>
                        <z>0</z>
                        <width>140</width>
                        <height>3</height>
                        <depth>0</depth>
                        <hotspotX>-0</hotspotX>
                        <hotspotY>0</hotspotY>
                        <angle>0</angle>
                        <opacity>1</opacity>
                    </world>
                </instance>
                <instance type="Sono" uid="16">
                    <properties>
                        <initial-visibility>Visible</initial-visibility>
                        <initial-animation>Default</initial-animation>
                        <initial-frame>0</initial-frame>
                        <collisions>Enabled</collisions>
                    </properties>
                    <blend-mode>0</blend-mode>
                    <effect-fallback>0</effect-fallback>
                    <world>
                        <x>146</x>
                        <y>157</y>
                        <z>0</z>
                        <width>50</width>
                        <height>3</height>
                        <depth>0</depth>
                        <hotspotX>0</hotspotX>
                        <hotspotY>0</hotspotY>
                        <angle>0</angle>
                        <opacity>1</opacity>
                    </world>
                </instance>
                <instance type="Xixi" uid="11">
                    <properties>
                        <initial-visibility>Visible</initial-visibility>
                        <initial-animation>Default</initial-animation>
                        <initial-frame>0</initial-frame>
                        <collisions>Enabled</collisions>
                    </properties>
                    <blend-mode>0</blend-mode>
                    <effect-fallback>0</effect-fallback>
                    <world>
                        <x>254</x>
                        <y>157</y>
                        <z>0</z>
                        <width>50</width>
                        <height>3</height>
                        <depth>0</depth>
                        <hotspotX>-0</hotspotX>
                        <hotspotY>0</hotspotY>
                        <angle>0</angle>
                        <opacity>1</opacity>
                    </world>
                </instance>
                <instance type="Fome" uid="14">
                    <properties>
                        <initial-visibility>Visible</initial-visibility>
                        <initial-animation>Default</initial-animation>
                        <initial-frame>0</initial-frame>
                        <collisions>Enabled</collisions>
                    </properties>
                    <blend-mode>0</blend-mode>
                    <effect-fallback>0</effect-fallback>
                    <world>
                        <x>38</x>
                        <y>157</y>
                        <z>0</z>
                        <width>50</width>
                        <height>3</height>
                        <depth>0</depth>
                        <hotspotX>-0</hotspotX>
                        <hotspotY>0</hotspotY>
                        <angle>0</angle>
                        <opacity>1</opacity>
                    </world>
                </instance>
                <instance type="Bug" uid="20">
                    <properties>
                        <initial-visibility>Visible</initial-visibility>
                        <initial-animation>Default</initial-animation>
                        <initial-frame>0</initial-frame>
                        <collisions>Enabled</collisions>
                    </properties>
                    <blend-mode>0</blend-mode>
                    <effect-fallback>0</effect-fallback>
                    <world>
                        <x>218</x>
                        <y>175</y>
                        <z>0</z>
                        <width>86</width>
                        <height>3</height>
                        <depth>0</depth>
                        <hotspotX>0</hotspotX>
                        <hotspotY>0</hotspotY>
                        <angle>0</angle>
                        <opacity>1</opacity>
                    </world>
                </instance>
                <instance type="Pbug" uid="32">
                    <properties>
                        <rate>1</rate>
                        <spray-cone>360</spray-cone>
                        <type>One-shot</type>
                        <initial-particle-properties></initial-particle-properties>
                        <speed>50</speed>
                        <size>18</size>
                        <opacity>100</opacity>
                        <grow-rate>0</grow-rate>
                        <x-randomiser>0</x-randomiser>
                        <y-randomiser>0</y-randomiser>
                        <speed-randomiser->0</speed-randomiser->
                        <size-randomiser>0</size-randomiser>
                        <grow-rate-randomiser>0</grow-rate-randomiser>
                        <particle-lifetime-properties></particle-lifetime-properties>
                        <acceleration>0</acceleration>
                        <gravity>0</gravity>
                        <angle-randomiser>0</angle-randomiser>
                        <speed-randomiser>800</speed-randomiser>
                        <opacity-randomiser>0</opacity-randomiser>
                        <destroy-mode>Fade to invisible</destroy-mode>
                        <timeout>1</timeout>
                    </properties>
                    <blend-mode>0</blend-mode>
                    <effect-fallback>0</effect-fallback>
                    <world>
                        <x>496.235778809</x>
                        <y>298.808044434</y>
                        <z>0</z>
                        <width>128</width>
                        <height>128</height>
                        <depth>0</depth>
                        <hotspotX>0</hotspotX>
                        <hotspotY>0.5</hotspotY>
                        <angle>0</angle>
                        <opacity>1</opacity>
                    </world>
                </instance>
            </instances>
            <effects />
        </layer>
    </layers>
    <nonworld-instances />
    <effects />
</c2layout>
